<?xml version='1.0' encoding='ISO-8859-1' ?>
<!DOCTYPE  utilisateurs [
<!ELEMENT utilisateurs ( utilisateur*)>

<!ELEMENT utilisateur (nom,prenom,login,password,mail,tel,avatar,datenaissance,adresse)>
<!ATTLIST utilisateur id  ID   #REQUIRED>
<!ATTLIST utilisateur type  CDATA  #REQUIRED>

<!ELEMENT nom (#PCDATA)>
<!ELEMENT prenom (#PCDATA)>
<!ELEMENT login (#PCDATA)>
<!ELEMENT password (#PCDATA)>
<!ELEMENT mail (#PCDATA)>
<!ELEMENT tel (#PCDATA)>
<!ELEMENT avatar (#PCDATA)>
<!ELEMENT datenaissance (#PCDATA)>
<!ELEMENT adresse (#PCDATA)>
]>


<utilisateurs>
	<utilisateur id="001" type="Etudiant">
		<nom>RANGA</nom>
		<prenom>Sathiya</prenom>
		<login>ranga</login>
		<password>pass1</password>
		<mail>sathiya@gmail.com</mail>
		<tel>015254545</tel>
		<avatar>C://documents/pf.gif</avatar>
		<datenaissance>13/05/1988</datenaissance>
		<adresse>70 rue .....</adresse>
	</utilisateur>
	<utilisateur id="007" type="Etudiant">
			<nom>BLANDIN</nom>
			<prenom>Willy</prenom>
			<login>Willy</login>
			<password>pass3</password>
			<mail>Willy@gmail.com</mail>
			<tel>015254545</tel>
			<avatar>C://documents/pf.gif</avatar>
			<datenaissance>13/05/1988</datenaissance>
			<adresse>70 rue .....</adresse>
	</utilisateur>
	<utilisateur id="002" type="Etudiant">
			<nom>SHAN</nom>
			<prenom>Suresh</prenom>
			<login>Suresh</login>
			<password>pass2</password>
			<mail>Suresh@gmail.com</mail>
			<tel>015254545</tel>
			<avatar>C://documents/pf.gif</avatar>
			<datenaissance>13/05/1988</datenaissance>
			<adresse>70 rue .....</adresse>
	</utilisateur>
	<utilisateur id="004" type="Enseignant">
			<matieres_ens>
				<matiere refmat="1"/>
				<matiere refmat="2"/>
				<matiere refmat="3"/>
				<matiere refmat="4"/>
			</matieres_ens>
			<nom>Denecker</nom>
			<prenom>Rebbecca</prenom>
			<login>rebbecca</login>
			<password>pass4</password>
			<mail>rebbecca@gmail.com</mail>
			<tel>015254545</tel>
			<avatar>C://documents/pf.gif</avatar>
			<fax>015454545</fax>
			<statut>Maître de conférence</statut>
			<adressebureau>70 rue .....</adressebureau>
			<telbureau>0152545565</telbureau>
			<ufr>UFR 27</ufr>
	</utilisateur>
	<utilisateur id="008" type="Enseignant">
			<matieres_ens>
				<matiere refmat="1"/>
			</matieres_ens>
			<nom>Pinheiro</nom>
			<prenom>Manuelle</prenom>
			<login>manuelle</login>
			<password>pass8</password>
			<mail>emmanuelle@gmail.com</mail>
			<tel>015254545</tel>
			<avatar>C://documents/pf.gif</avatar>
			<fax>015454545</fax>
			<statut>Maître de conférence</statut>
			<adressebureau>70 rue .....</adressebureau>
			<telbureau>0152545565</telbureau>
			<ufr>UFR 27</ufr>
	</utilisateur>
</utilisateurs>